kubetemp/__init__.py
kubetemp/cli.py
kubetemp/core.py
kubetemp-0.2.6.dist-info/LICENSE
kubetemp-0.2.6.dist-info/METADATA
kubetemp-0.2.6.dist-info/WHEEL
kubetemp-0.2.6.dist-info/entry_points.txt
kubetemp-0.2.6.dist-info/top_level.txt
kubetemp-0.2.6.dist-info/RECORD
