Metadata-Version: 2.1
Name: kubetemp
Version: 0.2.6
Summary: Tool for generating kubernetes (k8s) manifests using Jinja templates.
Home-page: https://github.com/jgv7/kubetemp
Author: Jared Vasquez
License: MIT
Platform: UNKNOWN
Classifier: Development Status :: 4 - Beta
Classifier: Intended Audience :: Developers
Classifier: Topic :: Software Development :: Build Tools
Classifier: License :: OSI Approved :: MIT License
Classifier: Programming Language :: Python :: 3.6
Classifier: Programming Language :: Python :: 3.7
Requires-Python: >=3.6
Requires-Dist: Click (>=7.0)
Requires-Dist: jinja2 (>=2.10)
Requires-Dist: PyYAML (<=3.13,>=3.10)
